trytond/modules/employee_timetracking/README.rst
trytond/modules/employee_timetracking/__init__.py
trytond/modules/employee_timetracking/accountrule.py
trytond/modules/employee_timetracking/accountrule.xml
trytond/modules/employee_timetracking/breakperiod.py
trytond/modules/employee_timetracking/breakperiod.xml
trytond/modules/employee_timetracking/breaktime.py
trytond/modules/employee_timetracking/breaktime.xml
trytond/modules/employee_timetracking/buttons.xml
trytond/modules/employee_timetracking/calendar2.py
trytond/modules/employee_timetracking/calendar2.xml
trytond/modules/employee_timetracking/colordef.xml
trytond/modules/employee_timetracking/colors.py
trytond/modules/employee_timetracking/colors.xml
trytond/modules/employee_timetracking/configwizard.py
trytond/modules/employee_timetracking/configwizard.xml
trytond/modules/employee_timetracking/const.py
trytond/modules/employee_timetracking/cron_jobs.xml
trytond/modules/employee_timetracking/dayofevaluation.py
trytond/modules/employee_timetracking/dayofevaluation.xml
trytond/modules/employee_timetracking/employee.py
trytond/modules/employee_timetracking/employee.xml
trytond/modules/employee_timetracking/employee_wizard.py
trytond/modules/employee_timetracking/employee_wizard.xml
trytond/modules/employee_timetracking/evaluation.py
trytond/modules/employee_timetracking/evaluation.xml
trytond/modules/employee_timetracking/evaluation_holidays.py
trytond/modules/employee_timetracking/evaluation_holidays.xml
trytond/modules/employee_timetracking/evaluation_report.py
trytond/modules/employee_timetracking/evaluation_report.xml
trytond/modules/employee_timetracking/evaluation_sickdays.py
trytond/modules/employee_timetracking/evaluation_sickdays.xml
trytond/modules/employee_timetracking/holiday.py
trytond/modules/employee_timetracking/holiday.xml
trytond/modules/employee_timetracking/icon.xml
trytond/modules/employee_timetracking/menu.xml
trytond/modules/employee_timetracking/period.py
mds_employee_timetracking-5.0.24.dist-info/METADATA
mds_employee_timetracking-5.0.24.dist-info/WHEEL
mds_employee_timetracking-5.0.24.dist-info/entry_points.txt
mds_employee_timetracking-5.0.24.dist-info/top_level.txt
mds_employee_timetracking-5.0.24.dist-info/RECORD
