Metadata-Version: 2.1
Name: mds-employee-timetracking
Version: 5.0.24
Summary: Tryton module for time tracking of a employee
Home-page: https://www.m-ds.de/
Author: m-ds
Author-email: service@m-ds.de
License: GPL-3
Keywords: tryton time tracking employee worktime
Platform: UNKNOWN
Classifier: Development Status :: 5 - Production/Stable
Classifier: Environment :: Plugins
Classifier: Framework :: Tryton
Classifier: Intended Audience :: Developers
Classifier: Intended Audience :: Customer Service
Classifier: Intended Audience :: Information Technology
Classifier: Intended Audience :: Financial and Insurance Industry
Classifier: Topic :: Office/Business
Classifier: Topic :: Office/Business :: Financial :: Accounting
Classifier: Natural Language :: German
Classifier: Natural Language :: English
Classifier: Operating System :: OS Independent
Classifier: License :: OSI Approved :: GNU General Public License (GPL)
Classifier: Programming Language :: Python :: 3.4
Classifier: Programming Language :: Python :: 3.5
Classifier: Programming Language :: Python :: 3.6
Classifier: Programming Language :: Python :: 3.7
Requires-Dist: mds-sqlextension (>=0.1.8)
Requires-Dist: pytz
Requires-Dist: trytond-company (<5.1,>=5.0)
Requires-Dist: mds-pim-calendar (<=5.0.99,>=5.0.0)
Requires-Dist: trytond (<5.1,>=5.0)
